simple_telegram_mcp/__init__.py
simple_telegram_mcp/__main__.py
simple_telegram_mcp/auth.py
simple_telegram_mcp/client.py
simple_telegram_mcp/config.py
simple_telegram_mcp/install.py
simple_telegram_mcp/mcp_app.py
simple_telegram_mcp/schemas.py
simple_telegram_mcp-0.1.10.dist-info/METADATA
simple_telegram_mcp-0.1.10.dist-info/WHEEL
simple_telegram_mcp-0.1.10.dist-info/entry_points.txt
simple_telegram_mcp-0.1.10.dist-info/licenses/LICENSE
simple_telegram_mcp-0.1.10.dist-info/RECORD
