Metadata-Version: 2.4
Name: simple-telegram-mcp
Version: 0.1.10
Summary: The simplest MCP server for interacting with Telegram
Author-email: Yaser Martinez Palenzuela <yaser.martinez@gmail.com>
Maintainer-email: Yaser Martinez Palenzuela <yaser.martinez@gmail.com>
License: MIT
License-File: LICENSE
Keywords: automation,http,llm,mcp,telegram
Classifier: Development Status :: 4 - Beta
Classifier: Intended Audience :: Developers
Classifier: License :: OSI Approved :: MIT License
Classifier: Programming Language :: Python :: 3
Classifier: Programming Language :: Python :: 3.10
Requires-Python: >=3.10
Requires-Dist: fastmcp
Requires-Dist: mcp>=1.1.3
Requires-Dist: pydantic>=2.0.0
Requires-Dist: python-dotenv
Requires-Dist: telethon
